{
    "Ar36": {
        "error": 0.00097707213003148281, 
        "fit": "linear", 
        "value": 0.0050630953428682131
    }, 
    "Ar37": {
        "error": 0.14307029069655727, 
        "fit": "linear", 
        "value": 0.098221392016517792
    }, 
    "Ar38": {
        "error": 0.14294440626567964, 
        "fit": "linear", 
        "value": 0.74977944567021182
    }, 
    "Ar39": {
        "error": 0.08978152193144702, 
        "fit": "linear", 
        "value": 70.055874828709122
    }, 
    "Ar40": {
        "error": 0.23920637170970038, 
        "fit": "linear", 
        "value": 289.55894354944013
    }, 
    "Ar41": {
        "error": 0.12450999992832155, 
        "fit": "average_SEM", 
        "value": 0.2361661143740639
    }
}