{
    "AX": {
        "error": 0.05997045475890591, 
        "fit": "average_SEM", 
        "value": -0.18614595523104072
    }, 
    "CDD": {
        "error": 0.0001973723240400336, 
        "fit": "average_SEM", 
        "value": 0.00018785883100160087
    }, 
    "H1": {
        "error": 0.11113249459956959, 
        "fit": "average_SEM", 
        "value": -0.03312303359659078
    }, 
    "H2": {
        "error": 0.13509137014742673, 
        "fit": "average_SEM", 
        "value": -0.23896698671839356
    }, 
    "L1": {
        "error": 0.17847214315909515, 
        "fit": "average_SEM", 
        "value": -0.12083194731579473
    }, 
    "L2": {
        "error": 0.14369342026512233, 
        "fit": "average_SEM", 
        "value": -0.03855742465433044
    }
}