{
    "AX": {
        "error": 0.06765462946706559, 
        "fit": "average_SEM", 
        "value": -0.2403656969467799
    }, 
    "CDD": {
        "error": 2.3176005847679183e-05, 
        "fit": "average_SEM", 
        "value": 3.4548749681562187e-06
    }, 
    "H1": {
        "error": 0.10582567452946849, 
        "fit": "average_SEM", 
        "value": -0.07144701244736401
    }, 
    "H2": {
        "error": 0.1310042509689512, 
        "fit": "average_SEM", 
        "value": 0.0063718258713682495
    }, 
    "L1": {
        "error": 0.1433447900613338, 
        "fit": "average_SEM", 
        "value": -0.08769157391507179
    }, 
    "L2": {
        "error": 0.11009859593689068, 
        "fit": "average_SEM", 
        "value": -0.05130990404221747
    }
}