{
    "AX": {
        "error": 0.07830213850630174, 
        "fit": "average_SEM", 
        "value": 0.01331212669586724
    }, 
    "CDD": {
        "error": 0.00023778259584313616, 
        "fit": "average_SEM", 
        "value": 0.0005000932167604332
    }, 
    "H1": {
        "error": 0.12918138696256404, 
        "fit": "average_SEM", 
        "value": -0.008249864612783616
    }, 
    "H2": {
        "error": 0.1314887306160379, 
        "fit": "average_SEM", 
        "value": -0.035560163627572666
    }, 
    "L1": {
        "error": 0.17332336405339907, 
        "fit": "average_SEM", 
        "value": -0.1327313082680727
    }, 
    "L2": {
        "error": 0.14451996248362903, 
        "fit": "average_SEM", 
        "value": 0.03101839178125374
    }
}