{
    "AX": {
        "error": 0.058259042108165626, 
        "fit": "average_SEM", 
        "value": 0.00496964925720628
    }, 
    "CDD": {
        "error": 7.904125100778958e-05, 
        "fit": "average_SEM", 
        "value": 3.8867347029736266e-05
    }, 
    "H1": {
        "error": 0.125250860551599, 
        "fit": "average_SEM", 
        "value": -0.0279172485160719
    }, 
    "H2": {
        "error": 0.11563472303651516, 
        "fit": "average_SEM", 
        "value": -0.04178917562433829
    }, 
    "L1": {
        "error": 0.14733187504313885, 
        "fit": "average_SEM", 
        "value": -0.13597034954000264
    }, 
    "L2": {
        "error": 0.13038189209795972, 
        "fit": "average_SEM", 
        "value": -0.0027023328468203543
    }
}