{
    "Ar36": {
        "error": 0.0011336509799458813, 
        "fit": "parabolic", 
        "value": 0.0047297389994281989
    }, 
    "Ar37": {
        "error": 0.14369313706764533, 
        "fit": "linear", 
        "value": 0.053213638630183246
    }, 
    "Ar38": {
        "error": 0.16936283394322627, 
        "fit": "linear", 
        "value": -0.14573309733051809
    }, 
    "Ar39": {
        "error": 0.008344615745085153, 
        "fit": "parabolic", 
        "value": 0.0013403232166223824
    }, 
    "Ar40": {
        "error": 0.14306961856131956, 
        "fit": "parabolic", 
        "value": 1.3032362084937907
    }, 
    "Ar41": {
        "error": 0.13185874281449383, 
        "fit": "average_SEM", 
        "value": 0.22810043304020333
    }
}